{"is_source_file": true, "format": "JavaScript (ESLint configuration)", "description": "Configuration file for ESLint that specifies rules and settings for linting JavaScript and React files.", "external_files": ["@eslint/js", "eslint-plugin-react"], "external_methods": [], "published": [], "classes": [], "methods": [], "calls": [], "search-terms": ["ESLint", "React", "linting", "JavaScript", "configuration"], "state": 2, "file_id": 8, "knowledge_revision": 17, "git_revision": "648c0d6b27e74aeeeba46259c288726179a9484e", "hash": "be6538e7523bc2e9da0743133d784136", "format-version": 4, "code-base-name": "tic_tac_toe_frontend", "filename": "tic_tac_toe_frontend/eslint.config.mjs", "revision_history": [{"17": "648c0d6b27e74aeeeba46259c288726179a9484e"}]}